build_subpfam-0.1.1.data/scripts/build_subpfam
scripts/__init__.py
scripts/build_clade_hmms.py
scripts/build_trees.py
scripts/extract_clades.py
build_subpfam-0.1.1.dist-info/LICENSE
build_subpfam-0.1.1.dist-info/METADATA
build_subpfam-0.1.1.dist-info/WHEEL
build_subpfam-0.1.1.dist-info/top_level.txt
build_subpfam-0.1.1.dist-info/RECORD
