Metadata-Version: 2.1
Name: build-subpfam
Version: 0.1.1
Summary: Build clade HMMs from a multiple sequence alignment file
Home-page: https://github.com/satriaphd/build_subpfam
Author: Satria A Kautsar
Author-email: satriaphd@gmail.com
License: UNKNOWN
Platform: UNKNOWN
Classifier: Programming Language :: Python :: 3
Requires-Python: >=3.6
Requires-Dist: ete3
Requires-Dist: six
